testpypiazapala/__init__.py
testpypiazapala/m_mod_azapala.py
testpypiazapala-0.0.1.dist-info/LICENSE.txt
testpypiazapala-0.0.1.dist-info/METADATA
testpypiazapala-0.0.1.dist-info/WHEEL
testpypiazapala-0.0.1.dist-info/top_level.txt
testpypiazapala-0.0.1.dist-info/RECORD
