Metadata-Version: 2.1
Name: testpypiazapala
Version: 0.0.1
Summary: My test package
Author-email: AZ <algobitpl@gmail.com>
License: MIT License
Keywords: testpypiazapala,name,surname,fun function
Classifier: Operating System :: POSIX :: Other
Classifier: Programming Language :: Python :: 3.12
Requires-Python: >=3.0
License-File: LICENSE.txt
Requires-Dist: numpy
